[
    {
        "firstName": "John",
        "lastName": "Smith",
        "courseList": [
            {
                "number": 1181,
                "subject": "CS",
                "title": "Intro to Programming"
            },
            {
                "number": 1182,
                "subject": "CS",
                "title": "Intro to Programming 2"
            },
            {
                "number": 2235,
                "subject": "CS",
                "title": "Data Structures"
            }
        ]
    },
    {
        "firstName": "Mary",
        "lastName": "Jones",
        "courseList": [
            {
                "number": 3307,
                "subject": "INFO",
                "title": "Systems Analysis and Design"
            },
            {
                "number":4407,
                "subject": "INFO",
                "title": "Database Design and Implementation"
            },
            {
                "number": 1182,
                "subject": "CS",
                "title": "Intro to Programming 2 2"
            }
        ]
    },
    {
        "firstName": "Steve",
        "lastName": "Williams",
        "courseList": [
            {
                "number": 1181,
                "subject": "CS",
                "title": "Intro to Programming"
            },
            {
                "number": 1182,
                "subject": "CS",
                "title": "Intro to Programming 2"
            },
            {
                "number":3307,
                "subject": "INFO",
                "title": "Title 2"
            }
        ]
    }
]